hosha_network/__init__.py
hosha_network/interface.py
hosha_network/ioput.py
hosha_network/processing.py
hosha_network/utils.py
hosha_network-1.0.0.dist-info/licenses/LICENSE
hosha_network-1.0.0.dist-info/METADATA
hosha_network-1.0.0.dist-info/WHEEL
hosha_network-1.0.0.dist-info/top_level.txt
hosha_network-1.0.0.dist-info/RECORD
