Metadata-Version: 2.4
Name: hosha-network
Version: 1.0.0
Summary: A Python library to construct detailed pedestrian-vehicle layered networks from macro-level road data.
Author-email: Hiroyuki Hasada <important83d@email.com>
License: MIT License
Project-URL: Homepage, https://github.com/hasada83d/hosha-network
Project-URL: Repository, https://github.com/hasada83d/hosha-network
Project-URL: Issue Tracker, https://github.com/hasada83d/hosha-network/issues
Requires-Python: >=3.8
License-File: LICENSE
Requires-Dist: pandas
Requires-Dist: geopandas
Requires-Dist: numpy
Requires-Dist: networkx
Requires-Dist: shapely
Provides-Extra: dev
Requires-Dist: pytest; extra == "dev"
Requires-Dist: black; extra == "dev"
Requires-Dist: build; extra == "dev"
Requires-Dist: twine; extra == "dev"
Dynamic: license-file
